[
  {
    "Type": "SoundWave",
    "Name": "Sh_Co_Swish_WoodSword_03",
    "Class": "UScriptClass'SoundWave'",
    "Flags": "RF_Public | RF_Standalone | RF_Transactional | RF_WasLoaded | RF_LoadCompleted",
    "Properties": {
      "NumChannels": 1,
      "SampleRate": 48000,
      "Duration": 0.4649375,
      "TotalSamples": 22317.0,
      "TimecodeOffset": {
        "NumOfSecondsSinceMidnight": 657.0333333333333
      }
    },
    "PlatformCuePoints": [],
    "CompressedFormatData": null,
    "RawData": null,
    "CompressedDataGuid": "94ACEFFE-43DF2C36-BF9EEAB7-8A0E4DC8",
    "RunningPlatformData": {
      "NumChunks": 2,
      "AudioFormat": "BINKA",
      "Chunks": [
        {
          "DataSize": 28,
          "AudioDataSize": 28,
          "SeekOffsetInAudioFrames": 0,
          "BulkData": {
            "BulkDataFlags": "BULKDATA_ForceInlinePayload",
            "ElementCount": 28,
            "SizeOnDisk": 28,
            "OffsetInFile": "0x52"
          }
        },
        {
          "DataSize": 6551,
          "AudioDataSize": 6551,
          "SeekOffsetInAudioFrames": 0,
          "BulkData": {
            "BulkDataFlags": "BULKDATA_PayloadAtEndOfFile | BULKDATA_PayloadInSeperateFile | BULKDATA_Force_NOT_InlinePayload | BULKDATA_NoOffsetFixUp",
            "ElementCount": 6551,
            "SizeOnDisk": 6551,
            "OffsetInFile": "0x0"
          }
        }
      ]
    }
  }
]