[
  {
    "Type": "SoundWave",
    "Name": "AW_Env_DungeonTrap_FireSpin_OneShot_Sizzle_01",
    "Class": "UScriptClass'SoundWave'",
    "Flags": "RF_Public | RF_Standalone | RF_Transactional | RF_WasLoaded | RF_LoadCompleted",
    "Properties": {
      "NumChannels": 1,
      "SampleRate": 48000,
      "Duration": 4.0959377,
      "TotalSamples": 196605.02,
      "TimecodeOffset": {
        "NumOfSecondsSinceMidnight": 169.83877083333334
      }
    },
    "PlatformCuePoints": [],
    "CompressedFormatData": null,
    "RawData": null,
    "CompressedDataGuid": "920DA86E-4F863175-7004A691-FD4C78A1",
    "RunningPlatformData": {
      "NumChunks": 2,
      "AudioFormat": "BINKA",
      "Chunks": [
        {
          "DataSize": 28,
          "AudioDataSize": 28,
          "SeekOffsetInAudioFrames": 0,
          "BulkData": {
            "BulkDataFlags": "BULKDATA_ForceInlinePayload",
            "ElementCount": 28,
            "SizeOnDisk": 28,
            "OffsetInFile": "0x52"
          }
        },
        {
          "DataSize": 60213,
          "AudioDataSize": 60213,
          "SeekOffsetInAudioFrames": 0,
          "BulkData": {
            "BulkDataFlags": "BULKDATA_PayloadAtEndOfFile | BULKDATA_PayloadInSeperateFile | BULKDATA_Force_NOT_InlinePayload | BULKDATA_NoOffsetFixUp",
            "ElementCount": 60213,
            "SizeOnDisk": 60213,
            "OffsetInFile": "0x0"
          }
        }
      ]
    }
  }
]