[
  {
    "Type": "SoundWave",
    "Name": "AW_Pl_Fo_FS_Boot_Carpet_Walk_06",
    "Class": "UScriptClass'SoundWave'",
    "Flags": "RF_Public | RF_Standalone | RF_Transactional | RF_WasLoaded | RF_LoadCompleted",
    "Properties": {
      "NumChannels": 1,
      "SampleRate": 48000,
      "Duration": 0.3544375,
      "TotalSamples": 17013.0,
      "TimecodeOffset": {
        "NumOfSecondsSinceMidnight": 3.7647083333333335
      }
    },
    "PlatformCuePoints": [],
    "CompressedFormatData": null,
    "RawData": null,
    "CompressedDataGuid": "0C567DA8-40A509C7-8045C3AB-7A6C9C85",
    "RunningPlatformData": {
      "NumChunks": 2,
      "AudioFormat": "BINKA",
      "Chunks": [
        {
          "DataSize": 28,
          "AudioDataSize": 28,
          "SeekOffsetInAudioFrames": 0,
          "BulkData": {
            "BulkDataFlags": "BULKDATA_ForceInlinePayload",
            "ElementCount": 28,
            "SizeOnDisk": 28,
            "OffsetInFile": "0x52"
          }
        },
        {
          "DataSize": 5305,
          "AudioDataSize": 5305,
          "SeekOffsetInAudioFrames": 0,
          "BulkData": {
            "BulkDataFlags": "BULKDATA_PayloadAtEndOfFile | BULKDATA_PayloadInSeperateFile | BULKDATA_Force_NOT_InlinePayload | BULKDATA_NoOffsetFixUp",
            "ElementCount": 5305,
            "SizeOnDisk": 5305,
            "OffsetInFile": "0x0"
          }
        }
      ]
    }
  }
]