[
  {
    "Type": "SoundWave",
    "Name": "AW_Pl_Fo_Cloth_Land_Small_01",
    "Class": "UScriptClass'SoundWave'",
    "Flags": "RF_Public | RF_Standalone | RF_Transactional | RF_WasLoaded | RF_LoadCompleted",
    "Properties": {
      "NumChannels": 1,
      "SampleRate": 48000,
      "Duration": 0.6189167,
      "TotalSamples": 29708.002,
      "TimecodeOffset": {
        "NumOfSecondsSinceMidnight": 0.9435625
      }
    },
    "PlatformCuePoints": [],
    "CompressedFormatData": null,
    "RawData": null,
    "CompressedDataGuid": "578D46FB-4D756AFD-555FC281-3EDF11A4",
    "RunningPlatformData": {
      "NumChunks": 2,
      "AudioFormat": "BINKA",
      "Chunks": [
        {
          "DataSize": 28,
          "AudioDataSize": 28,
          "SeekOffsetInAudioFrames": 0,
          "BulkData": {
            "BulkDataFlags": "BULKDATA_ForceInlinePayload",
            "ElementCount": 28,
            "SizeOnDisk": 28,
            "OffsetInFile": "0x52"
          }
        },
        {
          "DataSize": 8847,
          "AudioDataSize": 8847,
          "SeekOffsetInAudioFrames": 0,
          "BulkData": {
            "BulkDataFlags": "BULKDATA_PayloadAtEndOfFile | BULKDATA_PayloadInSeperateFile | BULKDATA_Force_NOT_InlinePayload | BULKDATA_NoOffsetFixUp",
            "ElementCount": 8847,
            "SizeOnDisk": 8847,
            "OffsetInFile": "0x0"
          }
        }
      ]
    }
  }
]