[
  {
    "Type": "SoundWave",
    "Name": "AW_Wo_EmMo_ToadMorphed_08",
    "Class": "UScriptClass'SoundWave'",
    "Flags": "RF_Public | RF_Standalone | RF_WasLoaded | RF_LoadCompleted",
    "Properties": {
      "NumChannels": 1,
      "SampleRate": 48000,
      "Duration": 1.205,
      "TotalSamples": 57840.004
    },
    "PlatformCuePoints": [],
    "CompressedFormatData": null,
    "RawData": null,
    "CompressedDataGuid": "18A1A568-448B137F-7C8CDCAC-664F36DD",
    "RunningPlatformData": {
      "NumChunks": 2,
      "AudioFormat": "BINKA",
      "Chunks": [
        {
          "DataSize": 28,
          "AudioDataSize": 28,
          "SeekOffsetInAudioFrames": 0,
          "BulkData": {
            "BulkDataFlags": "BULKDATA_ForceInlinePayload",
            "ElementCount": 28,
            "SizeOnDisk": 28,
            "OffsetInFile": "0x46"
          }
        },
        {
          "DataSize": 6025,
          "AudioDataSize": 6025,
          "SeekOffsetInAudioFrames": 0,
          "BulkData": {
            "BulkDataFlags": "BULKDATA_PayloadAtEndOfFile | BULKDATA_PayloadInSeperateFile | BULKDATA_Force_NOT_InlinePayload | BULKDATA_NoOffsetFixUp",
            "ElementCount": 6025,
            "SizeOnDisk": 6025,
            "OffsetInFile": "0x0"
          }
        }
      ]
    }
  }
]