[
  {
    "Type": "PathSplineActionBendAlongPath",
    "Name": "DA_PS_SpectralPath",
    "Class": "UScriptClass'PathSplineActionBendAlongPath'",
    "Flags": "RF_Public | RF_Standalone | RF_Transactional | RF_WasLoaded | RF_LoadCompleted",
    "Properties": {
      "OffsetZ": -5.0,
      "ScaleXY": 2.12,
      "Meshs": [
        {
          "ObjectName": "StaticMesh'SM_PathDecalPlane'",
          "ObjectPath": "RSDragonwilds/Content/Art/Env/Misc/Tools/PathAssets/SM_PathDecalPlane.2"
        }
      ],
      "OverrideMaterial": {
        "ObjectName": "Material'M_VFX_SpectralPath'",
        "ObjectPath": "RSDragonwilds/Content/Art/VFX/Library/Env/Fellhollow/SpectralPath/M_VFX_SpectralPath.0"
      },
      "ItemName": "SpectralPath"
    }
  }
]