[
  {
    "Type": "BodySetup",
    "Name": "BodySetup_0",
    "Outer": "SM_BO_Bush_Large",
    "Class": "UScriptClass'BodySetup'",
    "Flags": "RF_Transactional | RF_WasLoaded | RF_LoadCompleted",
    "Properties": {
      "DefaultInstance": {
        "ObjectType": "ECollisionChannel::ECC_WorldStatic",
        "CollisionProfileName": "BlockAll",
        "CollisionResponses": {
          "ResponseArray": [
            {
              "Channel": "Footstep",
              "Response": "ECollisionResponse::ECR_Block"
            },
            {
              "Channel": "WorldActor",
              "Response": "ECollisionResponse::ECR_Block"
            },
            {
              "Channel": "Projectile_PathTrace",
              "Response": "ECollisionResponse::ECR_Block"
            },
            {
              "Channel": "Projectile_Arrow",
              "Response": "ECollisionResponse::ECR_Block"
            },
            {
              "Channel": "FeetIK",
              "Response": "ECollisionResponse::ECR_Block"
            },
            {
              "Channel": "AudioOcclusion",
              "Response": "ECollisionResponse::ECR_Block"
            }
          ]
        }
      }
    },
    "BodySetupGuid": "7FFB004E447FA8B4FA9EC28AFE5FFAE1",
    "CookedFormatData": {
      "Chaos": {
        "BulkDataFlags": "BULKDATA_SingleUse | BULKDATA_ForceInlinePayload",
        "ElementCount": 18514,
        "SizeOnDisk": 18514,
        "OffsetInFile": "0x83"
      }
    }
  },
  {
    "Type": "NavCollision",
    "Name": "NavCollision_0",
    "Outer": "SM_BO_Bush_Large",
    "Class": "UScriptClass'NavCollision'",
    "Flags": "RF_Transactional | RF_WasLoaded | RF_LoadCompleted",
    "CookedFormatData": {
      "NavCollision_Chaos": {
        "BulkDataFlags": "BULKDATA_SingleUse | BULKDATA_ForceInlinePayload",
        "ElementCount": 70,
        "SizeOnDisk": 70,
        "OffsetInFile": "0x32"
      }
    }
  },
  {
    "Type": "StaticMesh",
    "Name": "SM_BO_Bush_Large",
    "Class": "UScriptClass'StaticMesh'",
    "Flags": "RF_Public | RF_Standalone | RF_Transactional | RF_WasLoaded | RF_LoadCompleted",
    "Properties": {
      "StaticMaterials": [
        {
          "MaterialInterface": {
            "ObjectName": "MaterialInstanceConstant'MI_Standard_Green'",
            "ObjectPath": "RSDragonwilds/Content/Materials/Environment/MI_Standard_Green.0"
          },
          "MaterialSlotName": "Grass",
          "ImportedMaterialSlotName": "Grass",
          "UVChannelData": {
            "bInitialized": true,
            "bOverrideDensities": false,
            "LocalUVDensities": 1164.1553,
            "LocalUVDensities[1]": 834.0513,
            "LocalUVDensities[2]": 0.0,
            "LocalUVDensities[3]": 0.0
          },
          "OverlayMaterialInterface": null
        }
      ],
      "LightmapUVDensity": 834.0513,
      "LightMapResolution": 64,
      "LightMapCoordinateIndex": 1,
      "ExtendedBounds": {
        "Origin": {
          "X": 0.06626129,
          "Y": 8.557457,
          "Z": 67.26155
        },
        "BoxExtent": {
          "X": 183.75906,
          "Y": 123.07607,
          "Z": 82.908615
        },
        "SphereRadius": 193.3727569580078
      }
    },
    "BodySetup": {
      "ObjectName": "BodySetup'SM_BO_Bush_Large:BodySetup_0'",
      "ObjectPath": "RSDragonwilds/Content/Art/Env/LevelDesign/District1/BlockoutMeshes/SM_BO_Bush_Large.0"
    },
    "NavCollision": {
      "ObjectName": "NavCollision'SM_BO_Bush_Large:NavCollision_0'",
      "ObjectPath": "RSDragonwilds/Content/Art/Env/LevelDesign/District1/BlockoutMeshes/SM_BO_Bush_Large.1"
    },
    "LightingGuid": "E024BFC2-4540B67A-A7B9A2A3-1E44599E",
    "RenderData": {
      "LODs": [
        {
          "Sections": [
            {
              "MaterialIndex": 0,
              "FirstIndex": 0,
              "NumTriangles": 336,
              "MinVertexIndex": 0,
              "MaxVertexIndex": 719,
              "bEnableCollision": true,
              "bCastShadow": true,
              "bForceOpaque": false,
              "bVisibleInRayTracing": true
            }
          ],
          "MaxDeviation": 0.0,
          "PositionVertexBuffer": {
            "Stride": 12,
            "NumVertices": 720
          },
          "VertexBuffer": {
            "NumTexCoords": 2,
            "NumVertices": 720,
            "Strides": -1,
            "UseHighPrecisionTangentBasis": false,
            "UseFullPrecisionUVs": false
          },
          "ColorVertexBuffer": {
            "Stride": 0,
            "NumVertices": 0
          },
          "CardRepresentationData": {
            "Bounds": {
              "Min": {
                "X": -184.69281,
                "Y": -115.518616,
                "Z": -16.647064
              },
              "Max": {
                "X": 184.82532,
                "Y": 132.63353,
                "Z": 151.17017
              },
              "IsValid": 1
            },
            "MaxLodLevel": 0,
            "bMostlyTwoSided": false,
            "CardBuildData": [
              {
                "OBB": {
                  "AxisX": {
                    "X": 0.0,
                    "Y": 1.0,
                    "Z": 0.0
                  },
                  "AxisY": {
                    "X": 0.0,
                    "Y": 0.0,
                    "Z": 1.0
                  },
                  "AxisZ": {
                    "X": -1.0,
                    "Y": 0.0,
                    "Z": 0.0
                  },
                  "Origin": {
                    "X": -54.933746,
                    "Y": 8.557457,
                    "Z": 71.71586
                  },
                  "Extent": {
                    "X": 124.07608,
                    "Y": 79.45431,
                    "Z": 135.0
                  }
                },
                "LODLevel": 0,
                "AxisAlignedDirectionIndex": 0
              },
              {
                "OBB": {
                  "AxisX": {
                    "X": 0.0,
                    "Y": 1.0,
                    "Z": 0.0
                  },
                  "AxisY": {
                    "X": 0.0,
                    "Y": 0.0,
                    "Z": 1.0
                  },
                  "AxisZ": {
                    "X": 1.0,
                    "Y": 0.0,
                    "Z": 0.0
                  },
                  "Origin": {
                    "X": 75.06625,
                    "Y": 8.557457,
                    "Z": 67.26155
                  },
                  "Extent": {
                    "X": 124.07608,
                    "Y": 83.908615,
                    "Z": 115.0
                  }
                },
                "LODLevel": 0,
                "AxisAlignedDirectionIndex": 1
              },
              {
                "OBB": {
                  "AxisX": {
                    "X": 1.0,
                    "Y": 0.0,
                    "Z": 0.0
                  },
                  "AxisY": {
                    "X": 0.0,
                    "Y": 0.0,
                    "Z": 1.0
                  },
                  "AxisZ": {
                    "X": 0.0,
                    "Y": -1.0,
                    "Z": 0.0
                  },
                  "Origin": {
                    "X": 0.06625366,
                    "Y": -31.442543,
                    "Z": 67.26155
                  },
                  "Extent": {
                    "X": 184.75906,
                    "Y": 83.908615,
                    "Z": 90.0
                  }
                },
                "LODLevel": 0,
                "AxisAlignedDirectionIndex": 2
              },
              {
                "OBB": {
                  "AxisX": {
                    "X": 1.0,
                    "Y": 0.0,
                    "Z": 0.0
                  },
                  "AxisY": {
                    "X": 0.0,
                    "Y": 0.0,
                    "Z": 1.0
                  },
                  "AxisZ": {
                    "X": 0.0,
                    "Y": 1.0,
                    "Z": 0.0
                  },
                  "Origin": {
                    "X": 0.06625366,
                    "Y": 68.557465,
                    "Z": 67.26155
                  },
                  "Extent": {
                    "X": 184.75906,
                    "Y": 83.908615,
                    "Z": 70.0
                  }
                },
                "LODLevel": 0,
                "AxisAlignedDirectionIndex": 3
              },
              {
                "OBB": {
                  "AxisX": {
                    "X": 1.0,
                    "Y": 0.0,
                    "Z": 0.0
                  },
                  "AxisY": {
                    "X": 0.0,
                    "Y": 1.0,
                    "Z": 0.0
                  },
                  "AxisZ": {
                    "X": 0.0,
                    "Y": 0.0,
                    "Z": -1.0
                  },
                  "Origin": {
                    "X": 0.06625366,
                    "Y": 8.557457,
                    "Z": 17.26155
                  },
                  "Extent": {
                    "X": 184.75906,
                    "Y": 124.07608,
                    "Z": 40.0
                  }
                },
                "LODLevel": 0,
                "AxisAlignedDirectionIndex": 4
              },
              {
                "OBB": {
                  "AxisX": {
                    "X": 1.0,
                    "Y": 0.0,
                    "Z": 0.0
                  },
                  "AxisY": {
                    "X": 0.0,
                    "Y": 1.0,
                    "Z": 0.0
                  },
                  "AxisZ": {
                    "X": 0.0,
                    "Y": 0.0,
                    "Z": 1.0
                  },
                  "Origin": {
                    "X": 0.06625366,
                    "Y": 8.557457,
                    "Z": 77.26155
                  },
                  "Extent": {
                    "X": 184.75906,
                    "Y": 124.07608,
                    "Z": 80.0
                  }
                },
                "LODLevel": 0,
                "AxisAlignedDirectionIndex": 5
              }
            ]
          }
        }
      ],
      "NaniteResources": {
        "StreamablePages": {
          "BulkDataFlags": "BULKDATA_None",
          "ElementCount": 0,
          "SizeOnDisk": 0,
          "OffsetInFile": "0x6FFE"
        },
        "AssemblyTransforms": [],
        "AssemblyBoneAttachmentData": null,
        "VoxelMaterialsMask": 0,
        "MeshBounds": {
          "Origin": {
            "X": 0.0,
            "Y": 0.0,
            "Z": 0.0
          },
          "BoxExtent": {
            "X": 0.0,
            "Y": 0.0,
            "Z": 0.0
          },
          "SphereRadius": 0.0
        },
        "PageRangeLookup": null,
        "NumRootPages": 0,
        "PositionPrecision": 0,
        "NormalPrecision": 0,
        "NumInputTriangles": 0,
        "NumInputVertices": 0,
        "NumInputMeshes": 0,
        "NumInputTexCoords": 0,
        "NumClusters": 0,
        "ResourceFlags": "NONE"
      },
      "Bounds": {
        "Origin": {
          "X": 0.06626129,
          "Y": 8.557457,
          "Z": 67.26155
        },
        "BoxExtent": {
          "X": 183.75906,
          "Y": 123.07607,
          "Z": 82.908615
        },
        "SphereRadius": 193.37276
      },
      "bLODsShareStaticLighting": true,
      "ScreenSize": [
        2.0,
        0.0,
        0.0,
        0.0,
        0.0,
        0.0,
        0.0,
        0.0
      ]
    }
  }
]