[
  {
    "Type": "Texture2D",
    "Name": "T_Build_Placement_L",
    "Class": "UScriptClass'Texture2D'",
    "Flags": "RF_Public | RF_Standalone | RF_WasLoaded | RF_LoadCompleted",
    "Properties": {
      "ImportedSize": {
        "X": 244,
        "Y": 85
      },
      "LightingGuid": "066E1055-4A4BB238-C553BFBB-67093721",
      "CompressionSettings": "TextureCompressionSettings::TC_EditorIcon",
      "NeverStream": true
    },
    "SizeX": 244,
    "SizeY": 85,
    "PackedData": 1,
    "PixelFormat": "PF_B8G8R8A8",
    "FirstMipToSerialize": 0,
    "Mips": [
      {
        "BulkData": {
          "BulkDataFlags": "BULKDATA_SingleUse | BULKDATA_ForceInlinePayload",
          "ElementCount": 82960,
          "SizeOnDisk": 82960,
          "OffsetInFile": "0x78"
        },
        "SizeX": 244,
        "SizeY": 85,
        "SizeZ": 1
      }
    ]
  }
]