[
  {
    "Type": "SoundWave",
    "Name": "AW_Cr_Fo_GiantRat_FacePaw_02",
    "Class": "UScriptClass'SoundWave'",
    "Flags": "RF_Public | RF_Standalone | RF_Transactional | RF_WasLoaded | RF_LoadCompleted",
    "Properties": {
      "NumChannels": 1,
      "SampleRate": 48000,
      "Duration": 1.8108125,
      "TotalSamples": 86919.0,
      "TimecodeOffset": {
        "NumOfSecondsSinceMidnight": 88.08091666666667
      }
    },
    "PlatformCuePoints": [
      {
        "CuePointID": 1,
        "Label": "AW_Cr_Fo_GiantRat_FacePaw_02",
        "FramePosition": 0,
        "FrameLength": 0,
        "bIsLoopRegion": false
      },
      {
        "CuePointID": 1,
        "Label": "",
        "FramePosition": 0,
        "FrameLength": 86918,
        "bIsLoopRegion": true
      }
    ],
    "CompressedFormatData": null,
    "RawData": null,
    "CompressedDataGuid": "851B3C25-46E9D1BD-9117F78B-889AF9DF",
    "RunningPlatformData": {
      "NumChunks": 2,
      "AudioFormat": "BINKA",
      "Chunks": [
        {
          "DataSize": 28,
          "AudioDataSize": 28,
          "SeekOffsetInAudioFrames": 0,
          "BulkData": {
            "BulkDataFlags": "BULKDATA_ForceInlinePayload",
            "ElementCount": 28,
            "SizeOnDisk": 28,
            "OffsetInFile": "0x8E"
          }
        },
        {
          "DataSize": 28327,
          "AudioDataSize": 28327,
          "SeekOffsetInAudioFrames": 0,
          "BulkData": {
            "BulkDataFlags": "BULKDATA_PayloadAtEndOfFile | BULKDATA_PayloadInSeperateFile | BULKDATA_Force_NOT_InlinePayload | BULKDATA_NoOffsetFixUp",
            "ElementCount": 28327,
            "SizeOnDisk": 28327,
            "OffsetInFile": "0x0"
          }
        }
      ]
    }
  }
]