[
  {
    "Type": "SoundWave",
    "Name": "Aw_CoSo_ApplyBarb_Sword",
    "Class": "UScriptClass'SoundWave'",
    "Flags": "RF_Public | RF_Standalone | RF_Transactional | RF_WasLoaded | RF_LoadCompleted",
    "Properties": {
      "NumChannels": 1,
      "SampleRate": 48000,
      "Duration": 2.8666666,
      "TotalSamples": 137600.0,
      "TimecodeOffset": {
        "NumOfSecondsSinceMidnight": 184.16664583333332
      }
    },
    "PlatformCuePoints": [],
    "CompressedFormatData": null,
    "RawData": null,
    "CompressedDataGuid": "91E2F649-472122BE-517A4A90-0D4BCD6A",
    "RunningPlatformData": {
      "NumChunks": 2,
      "AudioFormat": "BINKA",
      "Chunks": [
        {
          "DataSize": 28,
          "AudioDataSize": 28,
          "SeekOffsetInAudioFrames": 0,
          "BulkData": {
            "BulkDataFlags": "BULKDATA_ForceInlinePayload",
            "ElementCount": 28,
            "SizeOnDisk": 28,
            "OffsetInFile": "0x52"
          }
        },
        {
          "DataSize": 46523,
          "AudioDataSize": 46523,
          "SeekOffsetInAudioFrames": 0,
          "BulkData": {
            "BulkDataFlags": "BULKDATA_PayloadAtEndOfFile | BULKDATA_PayloadInSeperateFile | BULKDATA_Force_NOT_InlinePayload | BULKDATA_NoOffsetFixUp",
            "ElementCount": 46523,
            "SizeOnDisk": 46523,
            "OffsetInFile": "0x0"
          }
        }
      ]
    }
  }
]